knac/__init__.py
knac/knac.py
knac_helpers/__init__.py
knac_helpers/knac_helpers.py
knac_toolkit-1.0.2.dist-info/METADATA
knac_toolkit-1.0.2.dist-info/WHEEL
knac_toolkit-1.0.2.dist-info/top_level.txt
knac_toolkit-1.0.2.dist-info/RECORD
