Metadata-Version: 2.1
Name: knac-toolkit
Version: 1.0.2
Summary: Knowledge Augmented Clustering
Author-email: Szymon Bobek <szymon.bobek@gmail.com>
Project-URL: Homepage, https://github.com/sbobek/knac
Project-URL: Documentation, https://knac-toolkit.readthedocs.org
Project-URL: Issues, https://github.com/sbobek/knac/issues
Keywords: xai,clustering,explainability,model-agnostic,rule-based
Classifier: License :: OSI Approved :: MIT License
Classifier: Programming Language :: Python
Classifier: Programming Language :: Python :: 3
Requires-Python: >=3.8
Requires-Dist: pandas >=1.5.2
Requires-Dist: umap-learn >=0.5.1
Requires-Dist: anchor-exp >=0.0.2.0
Requires-Dist: lux-explainer >=1.0.1
Requires-Dist: seaborn >=0.12.1
Requires-Dist: plotly >=5.11.0
Requires-Dist: tabulate >=0.9.0
Requires-Dist: graphviz >=0.20.1
Requires-Dist: ipython >=8.22.1
